AKRUP/Blast.py
AKRUP/ColinearScan.py
AKRUP/Ks.py
AKRUP/__init__.py
AKRUP/ancestral_dotplot.py
AKRUP/ancestral_genome_seqs.py
AKRUP/ancestral_karyotype.py
AKRUP/blast_block_dotplot.py
AKRUP/dotplot_CSR_event.py
AKRUP/dotplot_trajectory.py
AKRUP/event_Correspondence.py
AKRUP/funcbase.py
AKRUP/geteventblock.py
AKRUP/inferred_ancestral_karyotype.py
AKRUP/ks_fig.py
AKRUP/load_blockinfo.py
AKRUP/run.py
AKRUP/example/CSR_dotplot.conf
AKRUP/example/Loadblock.conf
AKRUP/example/Polyploidy_CSR.conf
AKRUP/example/__init__.py
AKRUP/example/ancestral_plotfig.conf
AKRUP/example/ancestralseq.conf
AKRUP/example/blast_dotplot.conf
AKRUP/example/block_dotplot.conf
AKRUP/example/dotplot_trajectory.conf
AKRUP/example/event_block.conf
AKRUP/example/event_dotplot.conf
AKRUP/example/infer_anckaryotype.conf
AKRUP/example/ksdistribute.conf
AKRUP/example/run_ColinearScan.conf
AKRUP/example/run_blast.conf
AKRUP/example/run_ks.conf
AKRUP/ini/SeqStatistics.pm
AKRUP/ini/__init__.py
AKRUP/ini/blastp
AKRUP/ini/blastp.exe
AKRUP/ini/blockscan
AKRUP/ini/blockscan.exe
AKRUP/ini/calculate.Ks.pl
AKRUP/ini/clustalw2
AKRUP/ini/clustalw2.exe
AKRUP/ini/makeblastdb
AKRUP/ini/makeblastdb.exe
AKRUP-1.0.5.dist-info/LICENSE
AKRUP-1.0.5.dist-info/METADATA
AKRUP-1.0.5.dist-info/WHEEL
AKRUP-1.0.5.dist-info/entry_points.txt
AKRUP-1.0.5.dist-info/top_level.txt
AKRUP-1.0.5.dist-info/RECORD
