Metadata-Version: 2.1
Name: AKRUP
Version: 1.0.5
Summary: Ancestral Karyotype Reconstruction Universal Pipeline
Home-page: https://github.com/Genome-structure-evolution-analysis/AKRUP
Author: wangjiaqi
License: BSD License
Classifier: Intended Audience :: Science/Research
Classifier: Programming Language :: Python :: 3
Classifier: License :: OSI Approved :: BSD License
Classifier: Operating System :: OS Independent
License-File: LICENSE
Requires-Dist: numpy
Requires-Dist: matplotlib
Requires-Dist: click
Requires-Dist: pandas (>=1.1.0)
Requires-Dist: scipy
Requires-Dist: biopython
